edutermclient/__init__.py
edutermclient/edutermclient.py
edutermclient-0.2.1.dist-info/LICENSE
edutermclient-0.2.1.dist-info/METADATA
edutermclient-0.2.1.dist-info/WHEEL
edutermclient-0.2.1.dist-info/top_level.txt
edutermclient-0.2.1.dist-info/RECORD
