Metadata-Version: 2.1
Name: edutermclient
Version: 0.2.1
Summary: Library for connecting to the Eduterm API
Home-page: https://github.com/kennisnet/py-eduterm-client
Author: Wim Muskee
Author-email: w.muskee@kennisnet.nl
License: MIT
Keywords: eduterm client
Platform: UNKNOWN
Classifier: License :: OSI Approved :: MIT License
Classifier: Operating System :: OS Independent
Classifier: Programming Language :: Python :: 2.7
Classifier: Programming Language :: Python :: 3
Classifier: Topic :: Software Development :: Libraries
Requires-Dist: requests
